__init__.py
cli.py
config.py
server.py
apps/001_dom_visualizer.py
apps/010_introduction.py
apps/020_profiles.py
apps/030_roles.py
apps/040_hello_workflow.py
apps/050_documentation.py
apps/060_tasks.py
apps/070_history.py
apps/100_connect_with_botify.py
apps/110_parameter_buster.py
apps/120_link_graph.py
apps/130_gap_analysis.py
apps/200_workflow_genesis.py
apps/210_widget_examples.py
apps/220_roadmap.py
apps/230_dev_assistant.py
apps/240_simon_mcp.py
apps/300_blank_placeholder.py
apps/400_botify_trifecta.py
apps/430_tab_opener.py
apps/440_browser_automation.py
apps/450_stream_simulator.py
apps/510_text_field.py
apps/520_text_area.py
apps/530_dropdown.py
apps/540_checkboxes.py
apps/550_radios.py
apps/560_range.py
apps/570_switch.py
apps/580_upload.py
apps/610_markdown.py
apps/620_mermaid.py
apps/630_prism.py
apps/640_javascript.py
apps/710_pandas.py
apps/720_rich.py
apps/730_matplotlib.py
apps/810_webbrowser.py
apps/820_selenium.py
imports/__init__.py
imports/ai_dictdb.py
imports/ai_tool_discovery_simple_parser.py
imports/append_only_conversation.py
imports/ascii_displays.py
imports/botify_code_generation.py
imports/crud.py
imports/durable_backup_system.py
imports/importme.py
imports/mcp_orchestrator.py
imports/server_logging.py
imports/stream_orchestrator.py
imports/voice_synthesis.py
imports/botify/__init__.py
imports/botify/code_generators.py
imports/botify/true_schema_discoverer.py
imports/dom_processing/__init__.py
imports/dom_processing/ai_dom_beautifier.py
imports/dom_processing/enhanced_dom_processor.py
pipulate-1.2.1.dist-info/licenses/LICENSE
tools/__init__.py
tools/advanced_automation_tools.py
tools/botify_tools.py
tools/conversation_tools.py
tools/keychain_tools.py
tools/mcp_tools.py
tools/system_tools.py
pipulate-1.2.1.dist-info/METADATA
pipulate-1.2.1.dist-info/WHEEL
pipulate-1.2.1.dist-info/entry_points.txt
pipulate-1.2.1.dist-info/top_level.txt
pipulate-1.2.1.dist-info/RECORD
