Metadata-Version: 2.4
Name: pipulate
Version: 1.2.1
Summary: Local First AI SEO Software
Author-email: Mike Levin <pipulate@gmail.com>
License-Expression: MIT
Project-URL: Homepage, https://github.com/miklevin/pipulate/
Project-URL: Bug Tracker, https://github.com/miklevin/pipulate/issues
Project-URL: Documentation, https://pipulate.com/guide/
Keywords: seo,ai,llm,automation,local-first,nix,fasthtml,htmx,agentic
Classifier: Development Status :: 5 - Production/Stable
Classifier: Programming Language :: Python :: 3
Classifier: Operating System :: OS Independent
Classifier: Topic :: Scientific/Engineering :: Artificial Intelligence
Classifier: Topic :: Internet :: WWW/HTTP :: Indexing/Search
Classifier: Topic :: Software Development :: Libraries :: Application Frameworks
Requires-Python: >=3.8
License-File: LICENSE
Requires-Dist: python-fasthtml>=0.6.9
Requires-Dist: python-multipart>=0.0.6
Requires-Dist: selenium>=4.11.2
Requires-Dist: aiohttp>=3.8.0
Requires-Dist: nest-asyncio>=1.5.6
Requires-Dist: rich>=13.0.0
Requires-Dist: python-dotenv>=1.0.0
Requires-Dist: psutil>=5.9.0
Dynamic: license-file
